matchering/__init__.py
matchering/checker.py
matchering/core.py
matchering/defaults.py
matchering/dsp.py
matchering/loader.py
matchering/preview_creator.py
matchering/results.py
matchering/saver.py
matchering/stages.py
matchering/utils.py
matchering/limiter/__init__.py
matchering/limiter/hyrax.py
matchering/log/__init__.py
matchering/log/codes.py
matchering/log/exceptions.py
matchering/log/explanations.py
matchering/log/handlers.py
matchering/stage_helpers/__init__.py
matchering/stage_helpers/match_frequencies.py
matchering/stage_helpers/match_levels.py
matchering-2.0.6.dist-info/LICENSE
matchering-2.0.6.dist-info/METADATA
matchering-2.0.6.dist-info/WHEEL
matchering-2.0.6.dist-info/top_level.txt
matchering-2.0.6.dist-info/RECORD
